[
    {
        "question": "what is the college address?",
        "answer": "The college is located at: KPR Institute of Engineering and Technology, Arasur, Coimbatore."
    },
    {
        "question": "where is the college located?",
        "answer": "The college is located at: KPR Institute of Engineering and Technology, Arasur, Coimbatore."
    },
    {
        "question": "college location",
        "answer": "The college is located at: KPR Institute of Engineering and Technology, Arasur, Coimbatore."
    },
    {
        "question": "how to reach college?",
        "answer": "The college is located at: KPR Institute of Engineering and Technology, Arasur, Coimbatore."
    },
    {
        "question": "address of kpriet",
        "answer": "The college is located at: KPR Institute of Engineering and Technology, Arasur, Coimbatore."
    },
    {
        "question": "where is kpriet?",
        "answer": "The college is located at: KPR Institute of Engineering and Technology, Arasur, Coimbatore."
    },
    {
        "question": "give me the address of your college",
        "answer": "The college is located at: KPR Institute of Engineering and Technology, Arasur, Coimbatore."
    },
    {
        "question": "where exactly is kpriet located?",
        "answer": "The college is located at: KPR Institute of Engineering and Technology, Arasur, Coimbatore."
    },
    {
        "question": "tell me the location of the college",
        "answer": "The college is located at: KPR Institute of Engineering and Technology, Arasur, Coimbatore."
    },
    {
        "question": "college map location",
        "answer": "The college is located at: KPR Institute of Engineering and Technology, Arasur, Coimbatore."
    },
    {
        "question": "where is it?",
        "answer": "The college is located at: KPR Institute of Engineering and Technology, Arasur, Coimbatore."
    },
    {
        "question": "i need the college address",
        "answer": "The college is located at: KPR Institute of Engineering and Technology, Arasur, Coimbatore."
    },
    {
        "question": "what's your location?",
        "answer": "The college is located at: KPR Institute of Engineering and Technology, Arasur, Coimbatore."
    },
    {
        "question": "address please",
        "answer": "The college is located at: KPR Institute of Engineering and Technology, Arasur, Coimbatore."
    },
    {
        "question": "what is the contact number?",
        "answer": "You can contact the college at: 75488 88444 or 75488 88555."
    },
    {
        "question": "how can i contact the college?",
        "answer": "You can contact the college at: 75488 88444 or 75488 88555."
    },
    {
        "question": "phone number",
        "answer": "You can contact the college at: 75488 88444 or 75488 88555."
    },
    {
        "question": "give me the college phone number",
        "answer": "You can contact the college at: 75488 88444 or 75488 88555."
    },
    {
        "question": "who should i call for admission?",
        "answer": "You can contact the college at: 75488 88444 or 75488 88555."
    },
    {
        "question": "contact details",
        "answer": "You can contact the college at: 75488 88444 or 75488 88555."
    },
    {
        "question": "helpline number",
        "answer": "You can contact the college at: 75488 88444 or 75488 88555."
    },
    {
        "question": "admission contact number",
        "answer": "You can contact the college at: 75488 88444 or 75488 88555."
    },
    {
        "question": "what are the contact numbers?",
        "answer": "You can contact the college at: 75488 88444 or 75488 88555."
    },
    {
        "question": "telephone number",
        "answer": "You can contact the college at: 75488 88444 or 75488 88555."
    },
    {
        "question": "is there a number i can call?",
        "answer": "You can contact the college at: 75488 88444 or 75488 88555."
    },
    {
        "question": "mobile number of kpriet",
        "answer": "You can contact the college at: 75488 88444 or 75488 88555."
    },
    {
        "question": "how to call kpriet?",
        "answer": "You can contact the college at: 75488 88444 or 75488 88555."
    },
    {
        "question": "contact info",
        "answer": "You can contact the college at: 75488 88444 or 75488 88555."
    },
    {
        "question": "what is the fee structure?",
        "answer": "The fee structure varies by department and admission quota (Government/Management). Please contact the admission office at 75488 88444 for detailed fee information."
    },
    {
        "question": "how much is the tuition fee?",
        "answer": "The fee structure varies by department and admission quota (Government/Management). Please contact the admission office at 75488 88444 for detailed fee information."
    },
    {
        "question": "college fees",
        "answer": "The fee structure varies by department and admission quota (Government/Management). Please contact the admission office at 75488 88444 for detailed fee information."
    },
    {
        "question": "fees details",
        "answer": "The fee structure varies by department and admission quota (Government/Management). Please contact the admission office at 75488 88444 for detailed fee information."
    },
    {
        "question": "how much does it cost to study here?",
        "answer": "The fee structure varies by department and admission quota (Government/Management). Please contact the admission office at 75488 88444 for detailed fee information."
    },
    {
        "question": "hostel fee structure",
        "answer": "The fee structure varies by department and admission quota (Government/Management). Please contact the admission office at 75488 88444 for detailed fee information."
    },
    {
        "question": "what are the fees for btech?",
        "answer": "The fee structure varies by department and admission quota (Government/Management). Please contact the admission office at 75488 88444 for detailed fee information."
    },
    {
        "question": "tell me about the fee",
        "answer": "The fee structure varies by department and admission quota (Government/Management). Please contact the admission office at 75488 88444 for detailed fee information."
    },
    {
        "question": "what's the cost?",
        "answer": "The fee structure varies by department and admission quota (Government/Management). Please contact the admission office at 75488 88444 for detailed fee information."
    },
    {
        "question": "yearly fee",
        "answer": "The fee structure varies by department and admission quota (Government/Management). Please contact the admission office at 75488 88444 for detailed fee information."
    },
    {
        "question": "semester fee",
        "answer": "The fee structure varies by department and admission quota (Government/Management). Please contact the admission office at 75488 88444 for detailed fee information."
    },
    {
        "question": "can you provide the fee structure?",
        "answer": "The fee structure varies by department and admission quota (Government/Management). Please contact the admission office at 75488 88444 for detailed fee information."
    },
    {
        "question": "is the fee high?",
        "answer": "The fee structure varies by department and admission quota (Government/Management). Please contact the admission office at 75488 88444 for detailed fee information."
    },
    {
        "question": "admission fees",
        "answer": "The fee structure varies by department and admission quota (Government/Management). Please contact the admission office at 75488 88444 for detailed fee information."
    },
    {
        "question": "how are the placements?",
        "answer": "KPRIET has an excellent placement record with top recruiters like TCS, CTS, Wipro, and Infosys visiting the campus. The placement cell provides extensive training. For detailed statistics, visit the official website."
    },
    {
        "question": "placement records",
        "answer": "KPRIET has an excellent placement record with top recruiters like TCS, CTS, Wipro, and Infosys visiting the campus. The placement cell provides extensive training. For detailed statistics, visit the official website."
    },
    {
        "question": "highest package",
        "answer": "KPRIET has an excellent placement record with top recruiters like TCS, CTS, Wipro, and Infosys visiting the campus. The placement cell provides extensive training. For detailed statistics, visit the official website."
    },
    {
        "question": "which companies visit for placements?",
        "answer": "KPRIET has an excellent placement record with top recruiters like TCS, CTS, Wipro, and Infosys visiting the campus. The placement cell provides extensive training. For detailed statistics, visit the official website."
    },
    {
        "question": "average package",
        "answer": "KPRIET has an excellent placement record with top recruiters like TCS, CTS, Wipro, and Infosys visiting the campus. The placement cell provides extensive training. For detailed statistics, visit the official website."
    },
    {
        "question": "tell me about placement",
        "answer": "KPRIET has an excellent placement record with top recruiters like TCS, CTS, Wipro, and Infosys visiting the campus. The placement cell provides extensive training. For detailed statistics, visit the official website."
    },
    {
        "question": "do you provide placement?",
        "answer": "KPRIET has an excellent placement record with top recruiters like TCS, CTS, Wipro, and Infosys visiting the campus. The placement cell provides extensive training. For detailed statistics, visit the official website."
    },
    {
        "question": "placement percentage",
        "answer": "KPRIET has an excellent placement record with top recruiters like TCS, CTS, Wipro, and Infosys visiting the campus. The placement cell provides extensive training. For detailed statistics, visit the official website."
    },
    {
        "question": "top recruiters",
        "answer": "KPRIET has an excellent placement record with top recruiters like TCS, CTS, Wipro, and Infosys visiting the campus. The placement cell provides extensive training. For detailed statistics, visit the official website."
    },
    {
        "question": "is placement good here?",
        "answer": "KPRIET has an excellent placement record with top recruiters like TCS, CTS, Wipro, and Infosys visiting the campus. The placement cell provides extensive training. For detailed statistics, visit the official website."
    },
    {
        "question": "will i get a job?",
        "answer": "KPRIET has an excellent placement record with top recruiters like TCS, CTS, Wipro, and Infosys visiting the campus. The placement cell provides extensive training. For detailed statistics, visit the official website."
    },
    {
        "question": "placement statistics",
        "answer": "KPRIET has an excellent placement record with top recruiters like TCS, CTS, Wipro, and Infosys visiting the campus. The placement cell provides extensive training. For detailed statistics, visit the official website."
    },
    {
        "question": "how many students got placed?",
        "answer": "KPRIET has an excellent placement record with top recruiters like TCS, CTS, Wipro, and Infosys visiting the campus. The placement cell provides extensive training. For detailed statistics, visit the official website."
    },
    {
        "question": "placement cell",
        "answer": "KPRIET has an excellent placement record with top recruiters like TCS, CTS, Wipro, and Infosys visiting the campus. The placement cell provides extensive training. For detailed statistics, visit the official website."
    },
    {
        "question": "do you offer mba?",
        "answer": "Currently, KPRIET primarily focuses on Engineering and Technology programs (B.E/B.Tech and M.E/M.Tech). Please verify with the admission office regarding management courses."
    },
    {
        "question": "is mba available in kpriet?",
        "answer": "Currently, KPRIET primarily focuses on Engineering and Technology programs (B.E/B.Tech and M.E/M.Tech). Please verify with the admission office regarding management courses."
    },
    {
        "question": "mba course",
        "answer": "Currently, KPRIET primarily focuses on Engineering and Technology programs (B.E/B.Tech and M.E/M.Tech). Please verify with the admission office regarding management courses."
    },
    {
        "question": "details about mba",
        "answer": "Currently, KPRIET primarily focuses on Engineering and Technology programs (B.E/B.Tech and M.E/M.Tech). Please verify with the admission office regarding management courses."
    },
    {
        "question": "mba fee structure",
        "answer": "Currently, KPRIET primarily focuses on Engineering and Technology programs (B.E/B.Tech and M.E/M.Tech). Please verify with the admission office regarding management courses."
    },
    {
        "question": "mba admission",
        "answer": "Currently, KPRIET primarily focuses on Engineering and Technology programs (B.E/B.Tech and M.E/M.Tech). Please verify with the admission office regarding management courses."
    },
    {
        "question": "how is mba here?",
        "answer": "Currently, KPRIET primarily focuses on Engineering and Technology programs (B.E/B.Tech and M.E/M.Tech). Please verify with the admission office regarding management courses."
    },
    {
        "question": "tell me about management studies",
        "answer": "Currently, KPRIET primarily focuses on Engineering and Technology programs (B.E/B.Tech and M.E/M.Tech). Please verify with the admission office regarding management courses."
    },
    {
        "question": "pg courses mba",
        "answer": "Currently, KPRIET primarily focuses on Engineering and Technology programs (B.E/B.Tech and M.E/M.Tech). Please verify with the admission office regarding management courses."
    },
    {
        "question": "is hostel available?",
        "answer": "Yes, KPRIET provides separate hostel facilities for boys and girls with excellent amenities, Wi-Fi, and quality food. AC and Non-AC rooms are available."
    },
    {
        "question": "tell me about hostel facilities",
        "answer": "Yes, KPRIET provides separate hostel facilities for boys and girls with excellent amenities, Wi-Fi, and quality food. AC and Non-AC rooms are available."
    },
    {
        "question": "hostel fees",
        "answer": "Yes, KPRIET provides separate hostel facilities for boys and girls with excellent amenities, Wi-Fi, and quality food. AC and Non-AC rooms are available."
    },
    {
        "question": "how is the hostel food?",
        "answer": "Yes, KPRIET provides separate hostel facilities for boys and girls with excellent amenities, Wi-Fi, and quality food. AC and Non-AC rooms are available."
    },
    {
        "question": "ac hostel available?",
        "answer": "Yes, KPRIET provides separate hostel facilities for boys and girls with excellent amenities, Wi-Fi, and quality food. AC and Non-AC rooms are available."
    },
    {
        "question": "girls hostel",
        "answer": "Yes, KPRIET provides separate hostel facilities for boys and girls with excellent amenities, Wi-Fi, and quality food. AC and Non-AC rooms are available."
    },
    {
        "question": "boys hostel",
        "answer": "Yes, KPRIET provides separate hostel facilities for boys and girls with excellent amenities, Wi-Fi, and quality food. AC and Non-AC rooms are available."
    },
    {
        "question": "hostel rules",
        "answer": "Yes, KPRIET provides separate hostel facilities for boys and girls with excellent amenities, Wi-Fi, and quality food. AC and Non-AC rooms are available."
    },
    {
        "question": "can i get a hostel room?",
        "answer": "Yes, KPRIET provides separate hostel facilities for boys and girls with excellent amenities, Wi-Fi, and quality food. AC and Non-AC rooms are available."
    },
    {
        "question": "is hostel compulsory?",
        "answer": "Yes, KPRIET provides separate hostel facilities for boys and girls with excellent amenities, Wi-Fi, and quality food. AC and Non-AC rooms are available."
    },
    {
        "question": "hostel rooms",
        "answer": "Yes, KPRIET provides separate hostel facilities for boys and girls with excellent amenities, Wi-Fi, and quality food. AC and Non-AC rooms are available."
    },
    {
        "question": "do you have accommodation?",
        "answer": "Yes, KPRIET provides separate hostel facilities for boys and girls with excellent amenities, Wi-Fi, and quality food. AC and Non-AC rooms are available."
    },
    {
        "question": "where will i stay?",
        "answer": "Yes, KPRIET provides separate hostel facilities for boys and girls with excellent amenities, Wi-Fi, and quality food. AC and Non-AC rooms are available."
    },
    {
        "question": "hostel life",
        "answer": "Yes, KPRIET provides separate hostel facilities for boys and girls with excellent amenities, Wi-Fi, and quality food. AC and Non-AC rooms are available."
    },
    {
        "question": "is college bus available?",
        "answer": "The college operates a fleet of buses covering various routes in and around Coimbatore, Tirupur, and Erode to ensure safe and convenient transport for students."
    },
    {
        "question": "transport facility",
        "answer": "The college operates a fleet of buses covering various routes in and around Coimbatore, Tirupur, and Erode to ensure safe and convenient transport for students."
    },
    {
        "question": "bus route details",
        "answer": "The college operates a fleet of buses covering various routes in and around Coimbatore, Tirupur, and Erode to ensure safe and convenient transport for students."
    },
    {
        "question": "how many buses are there?",
        "answer": "The college operates a fleet of buses covering various routes in and around Coimbatore, Tirupur, and Erode to ensure safe and convenient transport for students."
    },
    {
        "question": "do buses cover tirupur?",
        "answer": "The college operates a fleet of buses covering various routes in and around Coimbatore, Tirupur, and Erode to ensure safe and convenient transport for students."
    },
    {
        "question": "transport fees",
        "answer": "The college operates a fleet of buses covering various routes in and around Coimbatore, Tirupur, and Erode to ensure safe and convenient transport for students."
    },
    {
        "question": "bus timing",
        "answer": "The college operates a fleet of buses covering various routes in and around Coimbatore, Tirupur, and Erode to ensure safe and convenient transport for students."
    },
    {
        "question": "do you have transport facility?",
        "answer": "The college operates a fleet of buses covering various routes in and around Coimbatore, Tirupur, and Erode to ensure safe and convenient transport for students."
    },
    {
        "question": "college transport",
        "answer": "The college operates a fleet of buses covering various routes in and around Coimbatore, Tirupur, and Erode to ensure safe and convenient transport for students."
    },
    {
        "question": "how to commute to college?",
        "answer": "The college operates a fleet of buses covering various routes in and around Coimbatore, Tirupur, and Erode to ensure safe and convenient transport for students."
    },
    {
        "question": "bus from coimbatore",
        "answer": "The college operates a fleet of buses covering various routes in and around Coimbatore, Tirupur, and Erode to ensure safe and convenient transport for students."
    },
    {
        "question": "bus facilities",
        "answer": "The college operates a fleet of buses covering various routes in and around Coimbatore, Tirupur, and Erode to ensure safe and convenient transport for students."
    },
    {
        "question": "what courses do you offer?",
        "answer": "We offer various UG programs including AI & DS, Biomedical, Chemical, Civil, CSE, CSE (AIML), CSBS, Cyber Security, ECE, EEE, IT, Mechanical, and Mechatronics."
    },
    {
        "question": "list of departments",
        "answer": "We offer various UG programs including AI & DS, Biomedical, Chemical, Civil, CSE, CSE (AIML), CSBS, Cyber Security, ECE, EEE, IT, Mechanical, and Mechatronics."
    },
    {
        "question": "available branches",
        "answer": "We offer various UG programs including AI & DS, Biomedical, Chemical, Civil, CSE, CSE (AIML), CSBS, Cyber Security, ECE, EEE, IT, Mechanical, and Mechatronics."
    },
    {
        "question": "which engineering branch is best?",
        "answer": "We offer various UG programs including AI & DS, Biomedical, Chemical, Civil, CSE, CSE (AIML), CSBS, Cyber Security, ECE, EEE, IT, Mechanical, and Mechatronics."
    },
    {
        "question": "btech courses",
        "answer": "We offer various UG programs including AI & DS, Biomedical, Chemical, Civil, CSE, CSE (AIML), CSBS, Cyber Security, ECE, EEE, IT, Mechanical, and Mechatronics."
    },
    {
        "question": "be courses",
        "answer": "We offer various UG programs including AI & DS, Biomedical, Chemical, Civil, CSE, CSE (AIML), CSBS, Cyber Security, ECE, EEE, IT, Mechanical, and Mechatronics."
    },
    {
        "question": "do you have cse?",
        "answer": "We offer various UG programs including AI & DS, Biomedical, Chemical, Civil, CSE, CSE (AIML), CSBS, Cyber Security, ECE, EEE, IT, Mechanical, and Mechatronics."
    },
    {
        "question": "do you have artificial intelligence?",
        "answer": "We offer various UG programs including AI & DS, Biomedical, Chemical, Civil, CSE, CSE (AIML), CSBS, Cyber Security, ECE, EEE, IT, Mechanical, and Mechatronics."
    },
    {
        "question": "what are the branches available?",
        "answer": "We offer various UG programs including AI & DS, Biomedical, Chemical, Civil, CSE, CSE (AIML), CSBS, Cyber Security, ECE, EEE, IT, Mechanical, and Mechatronics."
    },
    {
        "question": "departments in kpriet",
        "answer": "We offer various UG programs including AI & DS, Biomedical, Chemical, Civil, CSE, CSE (AIML), CSBS, Cyber Security, ECE, EEE, IT, Mechanical, and Mechatronics."
    },
    {
        "question": "ug courses",
        "answer": "We offer various UG programs including AI & DS, Biomedical, Chemical, Civil, CSE, CSE (AIML), CSBS, Cyber Security, ECE, EEE, IT, Mechanical, and Mechatronics."
    },
    {
        "question": "pg courses",
        "answer": "We offer various UG programs including AI & DS, Biomedical, Chemical, Civil, CSE, CSE (AIML), CSBS, Cyber Security, ECE, EEE, IT, Mechanical, and Mechatronics."
    },
    {
        "question": "degrees offered",
        "answer": "We offer various UG programs including AI & DS, Biomedical, Chemical, Civil, CSE, CSE (AIML), CSBS, Cyber Security, ECE, EEE, IT, Mechanical, and Mechatronics."
    },
    {
        "question": "courses available",
        "answer": "We offer various UG programs including AI & DS, Biomedical, Chemical, Civil, CSE, CSE (AIML), CSBS, Cyber Security, ECE, EEE, IT, Mechanical, and Mechatronics."
    },
    {
        "question": "hi",
        "answer": "Hello! I am the KPRIET Chatbot. How can I help you today?"
    },
    {
        "question": "hello",
        "answer": "Hello! I am the KPRIET Chatbot. How can I help you today?"
    },
    {
        "question": "hey",
        "answer": "Hello! I am the KPRIET Chatbot. How can I help you today?"
    },
    {
        "question": "good morning",
        "answer": "Hello! I am the KPRIET Chatbot. How can I help you today?"
    },
    {
        "question": "good afternoon",
        "answer": "Hello! I am the KPRIET Chatbot. How can I help you today?"
    },
    {
        "question": "good evening",
        "answer": "Hello! I am the KPRIET Chatbot. How can I help you today?"
    },
    {
        "question": "namaste",
        "answer": "Hello! I am the KPRIET Chatbot. How can I help you today?"
    },
    {
        "question": "hi there",
        "answer": "Hello! I am the KPRIET Chatbot. How can I help you today?"
    },
    {
        "question": "hello chatbot",
        "answer": "Hello! I am the KPRIET Chatbot. How can I help you today?"
    },
    {
        "question": "hey buddy",
        "answer": "Hello! I am the KPRIET Chatbot. How can I help you today?"
    },
    {
        "question": "who are you?",
        "answer": "I am an AI chatbot designed to answer your queries about KPR Institute of Engineering and Technology."
    },
    {
        "question": "what is your name?",
        "answer": "I am an AI chatbot designed to answer your queries about KPR Institute of Engineering and Technology."
    },
    {
        "question": "are you a human?",
        "answer": "I am an AI chatbot designed to answer your queries about KPR Institute of Engineering and Technology."
    },
    {
        "question": "what can you do?",
        "answer": "I am an AI chatbot designed to answer your queries about KPR Institute of Engineering and Technology."
    },
    {
        "question": "how can you help me?",
        "answer": "I am an AI chatbot designed to answer your queries about KPR Institute of Engineering and Technology."
    },
    {
        "question": "about you",
        "answer": "I am an AI chatbot designed to answer your queries about KPR Institute of Engineering and Technology."
    },
    {
        "question": "your name",
        "answer": "I am an AI chatbot designed to answer your queries about KPR Institute of Engineering and Technology."
    }
]